{"judges":[],"court":"Court of Appeals of Virginia","api_url":"opinions\/0057063.json","author":null,"text":{"pdf":"http:\/\/www.courts.state.va.us\/opinions\/opncavwp\/0057063.pdf","text":"opinions\/0057063.txt"},"cited_laws":null,"cited_cases":null,"number":"0057063","name":"Joshua Paul Coyle v. Commonwealth of Virginia","date_published":"1\/27\/2007","parties":{"plaintiff":"Joshua Paul Coyle","defendant":"Commonwealth of Virginia"},"attorneys":[],"outcome":null,"type":null,"is_published":true}