{"judges":[],"court":"Court of Appeals of Virginia","api_url":"opinions\/0062962.json","author":null,"text":{"pdf":"http:\/\/www.courts.state.va.us\/opinions\/opncavwp\/0062962.pdf","text":"opinions\/0062962.txt"},"cited_laws":null,"cited_cases":null,"number":"0062962","name":"Actuarial Benefits, etc. v VEC &amp; Rosemary Lipcsey","date_published":"2\/17\/1996","parties":{"plaintiff":"Actuarial Benefits, etc.","defendant":"VEC &amp; Rosemary Lipcsey"},"attorneys":[],"outcome":null,"type":null,"is_published":true}