{"judges":[],"court":"Court of Appeals of Virginia","api_url":"opinions\/0271982.json","author":null,"text":{"pdf":"http:\/\/www.courts.state.va.us\/opinions\/opncavwp\/0271982.pdf","text":"opinions\/0271982.txt"},"cited_laws":null,"cited_cases":null,"number":"0271982","name":"Celesteen Viola Yancey,s\/k\/a CelestineV.Yancy v CW","date_published":"8\/31\/1999","parties":{"plaintiff":"Celesteen Viola Yancey,s\/k\/a CelestineV.Yancy","defendant":"CW"},"attorneys":[],"outcome":null,"type":null,"is_published":true}