{"judges":[],"court":"Court of Appeals of Virginia","api_url":"opinions\/0406054.json","author":null,"text":{"pdf":"http:\/\/www.courts.state.va.us\/opinions\/opncavwp\/0406054.pdf","text":"opinions\/0406054.txt"},"cited_laws":null,"cited_cases":null,"number":"0406054","name":"Robert William Eberth v. County of Prince William","date_published":"2\/05\/2006","parties":{"plaintiff":"Robert William Eberth","defendant":"County of Prince William"},"attorneys":[],"outcome":null,"type":null,"is_published":true}