{"judges":[],"court":"Court of Appeals of Virginia","api_url":"opinions\/0659002.json","author":null,"text":{"pdf":"http:\/\/www.courts.state.va.us\/opinions\/opncavwp\/0659002.pdf","text":"opinions\/0659002.txt"},"cited_laws":null,"cited_cases":null,"number":"0659002","name":"Southside VA Training Ctr\/CW v Frederick W. Ellis","date_published":"1\/21\/2000","parties":{"plaintiff":"Southside VA Training Ctr\/CW","defendant":"Frederick W. Ellis"},"attorneys":[],"outcome":null,"type":null,"is_published":true}