{"judges":[],"court":"Court of Appeals of Virginia","api_url":"opinions\/0707032.json","author":null,"text":{"pdf":"http:\/\/www.courts.state.va.us\/opinions\/opncavwp\/0707032.pdf","text":"opinions\/0707032.txt"},"cited_laws":null,"cited_cases":null,"number":"0707032","name":"Edward A. Vasaio v Dept. Motor Vehicles,Commonweal","date_published":"1\/13\/2004","parties":{"plaintiff":"Edward A. Vasaio","defendant":"Dept. Motor Vehicles,Commonweal"},"attorneys":[],"outcome":null,"type":null,"is_published":true}