{"judges":[],"court":"Court of Appeals of Virginia","api_url":"opinions\/1423981.json","author":null,"text":{"pdf":"http:\/\/www.courts.state.va.us\/opinions\/opncavwp\/1423981.pdf","text":"opinions\/1423981.txt"},"cited_laws":null,"cited_cases":null,"number":"1423981","name":"Marvin Walter Haskins v Commonwealth of Virginia","date_published":"2\/07\/1999","parties":{"plaintiff":"Marvin Walter Haskins","defendant":"Commonwealth of Virginia"},"attorneys":[],"outcome":null,"type":null,"is_published":true}