{"judges":[],"court":"Court of Appeals of Virginia","api_url":"opinions\/1461034.json","author":null,"text":{"pdf":"http:\/\/www.courts.state.va.us\/opinions\/opncavwp\/1461034.pdf","text":"opinions\/1461034.txt"},"cited_laws":null,"cited_cases":null,"number":"1461034","name":"Naheed Saeed Morrill v. Clarence Grant Morrill, II","date_published":"8\/17\/2004","parties":{"plaintiff":"Naheed Saeed Morrill","defendant":"Clarence Grant Morrill, II"},"attorneys":[],"outcome":null,"type":null,"is_published":true}