{"judges":[],"court":"Court of Appeals of Virginia","api_url":"opinions\/1875983.json","author":null,"text":{"pdf":"http:\/\/www.courts.state.va.us\/opinions\/opncavwp\/1875983.pdf","text":"opinions\/1875983.txt"},"cited_laws":null,"cited_cases":null,"number":"1875983","name":"Kathy Jo Dotson v Jeffery S. and Janice Hylton","date_published":"5\/04\/1999","parties":{"plaintiff":"Kathy Jo Dotson","defendant":"Jeffery S. and Janice Hylton"},"attorneys":[],"outcome":null,"type":null,"is_published":true}