{"judges":[],"court":"Court of Appeals of Virginia","api_url":"opinions\/2041012.json","author":null,"text":{"pdf":"http:\/\/www.courts.state.va.us\/opinions\/opncavwp\/2041012.pdf","text":"opinions\/2041012.txt"},"cited_laws":null,"cited_cases":null,"number":"2041012","name":"CW, DSS, DCSE, Spotsylvania CO DSS v Fletcher","date_published":"4\/16\/2002","parties":{"plaintiff":"CW, DSS, DCSE, Spotsylvania CO DSS","defendant":"Fletcher"},"attorneys":[],"outcome":null,"type":null,"is_published":true}