{"judges":[],"court":"Court of Appeals of Virginia","api_url":"opinions\/2111932.json","author":null,"text":{"pdf":"http:\/\/www.courts.state.va.us\/opinions\/opncavwp\/2111932.pdf","text":"opinions\/2111932.txt"},"cited_laws":null,"cited_cases":null,"number":"2111932","name":"Murray L. Steinberg v. Katherine T. Steinberg, etc","date_published":"9\/05\/1995","parties":{"plaintiff":"Murray L. Steinberg","defendant":"Katherine T. Steinberg, etc"},"attorneys":[],"outcome":null,"type":null,"is_published":true}