{"judges":[],"court":"Court of Appeals of Virginia","api_url":"opinions\/2116963.json","author":null,"text":{"pdf":"http:\/\/www.courts.state.va.us\/opinions\/opncavwp\/2116963.pdf","text":"opinions\/2116963.txt"},"cited_laws":null,"cited_cases":null,"number":"2116963","name":"Uninsured Employer's Fund v Harold C. Mounts, etal","date_published":"4\/22\/1997","parties":{"plaintiff":"Uninsured Employer's Fund","defendant":"Harold C. Mounts, etal"},"attorneys":[],"outcome":null,"type":null,"is_published":true}