{"judges":[],"court":"Court of Appeals of Virginia","api_url":"opinions\/2700031.json","author":null,"text":{"pdf":"http:\/\/www.courts.state.va.us\/opinions\/opncavwp\/2700031.pdf","text":"opinions\/2700031.txt"},"cited_laws":null,"cited_cases":null,"number":"2700031","name":"Alliance to Save the Mattaponi, et al. v. Virginia Marine Resources Commissin, et al.","date_published":"8\/31\/2004","parties":{"plaintiff":"Alliance to Save the Mattaponi, et al.","defendant":"Virginia Marine Resources Commissin, et al."},"attorneys":[],"outcome":null,"type":null,"is_published":true}